Metadata-Version: 1.0
Name: pygel
Version: 0.6.4
Summary: An implementation of some functionalities of gobject/glib/gio in pure python, but adding a lot of new features.
Home-page: http://github.com/caetanus/pygel
Author: Marcelo Aires Caetano
Author-email: marcelo@fiveti.com
License: BSD
Keywords: event library,file monitor,watchdog
Platform: UNKNOWN
